{
  "experiment": "EXP-001: Proto-Belief Emergence",
  "hypothesis": "H3 \u2014 Stable shared belief structures emerge from noise via simple local interaction rules",
  "baseline": {
    "initial_diversity": 0.7678336993197495,
    "final_diversity": 0.28398282000710845,
    "initial_clusters": 98,
    "final_clusters": 56,
    "final_largest_cluster_frac": 0.08,
    "final_belief_variance": 0.011551518263027444
  },
  "falsification": [
    {
      "test": "high_noise",
      "noise_level": 0.3,
      "final_clusters": 100,
      "final_diversity": 1.0069194122746732,
      "final_largest_frac": 0.01,
      "final_belief_variance": 0.11342066104047877,
      "theory_survived": false
    },
    {
      "test": "contrarians",
      "fraction": 0.2,
      "final_clusters": 76,
      "final_diversity": 0.675210487501804,
      "final_largest_frac": 0.04,
      "final_belief_variance": 0.07258074447050897,
      "theory_survived": false
    },
    {
      "test": "agent_failures",
      "failure_rate": 0.3,
      "final_alive": 71,
      "final_clusters": 59,
      "final_largest_frac": 0.04225352112676056,
      "final_diversity": 0.4131528172955063,
      "final_belief_variance": 0.030541957002256193,
      "theory_survived": false
    },
    {
      "test": "random_rules",
      "mutation_rate": 0.1,
      "final_clusters": 56,
      "final_largest_frac": 0.09,
      "final_diversity": 0.2770199513624185,
      "final_belief_variance": 0.011483535193962151,
      "theory_survived": true
    }
  ],
  "falsification_survived": "1/4",
  "replication": {
    "n_runs": 10,
    "diversity_mean": 0.3168795263974561,
    "diversity_std": 0.009162082340337534,
    "clusters_mean": 64.0,
    "clusters_std": 4.123105625617661,
    "largest_mean": 0.067,
    "largest_std": 0.011874342087037918,
    "consistent": true
  },
  "tournament": {
    "scores": {
      "H1: Information Entropy Decay": {
        "prediction_accuracy": 0.2,
        "robustness": 0.5,
        "novelty": 0.7,
        "simplicity": 0.5,
        "explanatory_power": 0.3,
        "total": 0.39999999999999997
      },
      "H2: Fractal Neural Dynamics": {
        "prediction_accuracy": 0.2,
        "robustness": 0.5,
        "novelty": 0.6,
        "simplicity": 0.5,
        "explanatory_power": 0.3,
        "total": 0.385
      },
      "H3: Proto-Belief Emergence": {
        "prediction_accuracy": 1.0,
        "robustness": 1.0,
        "novelty": 0.8,
        "simplicity": 0.9,
        "explanatory_power": 0.33999999999999997,
        "total": 0.828
      },
      "H4: Specialization-Creativity Tradeoff": {
        "prediction_accuracy": 0.2,
        "robustness": 0.5,
        "novelty": 0.4,
        "simplicity": 0.5,
        "explanatory_power": 0.3,
        "total": 0.355
      }
    },
    "winner": "H3: Proto-Belief Emergence"
  },
  "verdict": "DOMAIN_VALID",
  "domain_of_validity": {
    "noise_threshold": 0.15,
    "contrarian_threshold": 0.15,
    "description": "Theory holds under low-to-moderate noise and few contrarians"
  }
}